{
  "project_info": {
    "project_number": "827609479411",
    "project_id": "trustofficereader",
    "storage_bucket": "trustofficereader.appspot.com"
  },
  "client": [
    {
      "client_info": {
        "mobilesdk_app_id": "1:827609479411:android:982d55cebbf81347d49f86",
        "android_client_info": {
          "package_name": "com.ntdapp.document.viewer.reader.officereader.pdfreader"
        }
      },
      "oauth_client": [
        {
          "client_id": "827609479411-jdja54hrhinvr16uot62j8s2r5qi3j58.apps.googleusercontent.com",
          "client_type": 3
        }
      ],
      "api_key": [
        {
          "current_key": "AIzaSyDj8Ya-90aMSndNkKKFkc0K3fOwQbevDIQ"
        }
      ],
      "services": {
        "appinvite_service": {
          "other_platform_oauth_client": [
            {
              "client_id": "827609479411-jdja54hrhinvr16uot62j8s2r5qi3j58.apps.googleusercontent.com",
              "client_type": 3
            }
          ]
        }
      }
    }
  ],
  "configuration_version": "1"
}